facebook/__init__.py
facebook/version.py
facebook_sdk_nromero-4.0.2.dist-info/LICENSE
facebook_sdk_nromero-4.0.2.dist-info/METADATA
facebook_sdk_nromero-4.0.2.dist-info/WHEEL
facebook_sdk_nromero-4.0.2.dist-info/top_level.txt
facebook_sdk_nromero-4.0.2.dist-info/RECORD
