Metadata-Version: 2.1
Name: facebook-sdk-nromero
Version: 4.0.2
Summary: This client library (fork) is designed to support the Facebook Graph API (v16) and the official Facebook JavaScript SDK, which is the canonical way to implement Facebook authentication.
Home-page: https://github.com/nicanor-romero/facebook-sdk
Author: Facebook
Maintainer: Nicanor Romero
Maintainer-email: martey+facebook-sdk@mobolic.com
License: Apache
Platform: UNKNOWN
Classifier: License :: OSI Approved :: Apache Software License
Classifier: Programming Language :: Python
Classifier: Programming Language :: Python :: 3
Classifier: Programming Language :: Python :: 3.5
Classifier: Programming Language :: Python :: 3.6
Classifier: Programming Language :: Python :: 3.7
Classifier: Programming Language :: Python :: 3.8
Classifier: Programming Language :: Python :: 3.9
Requires-Dist: requests
